{
  "main": {
    "name":"Joy Chen",
    "description":"aspiring software development engineer. I use react and javascript to develop applications. This website serves as a testimony to my skillsets",
    "image":"profile.png",
    "bio":"Use this bio section as your way of describing yourself and saying what you do, what technologies you like to use or feel most comfortable with, describing your personality, or whatever else you feel like throwing in.",
    "contactmessage":"Here is where you should write your message to readers to have them get in contact with you.",
    "email": "joychen5069@gmail.com",
    "phone": "919-448-4416",
    "github":"https://github.com/joychen5069",
    "resume":"https://github.com/joychen5069/ReactPortfolio",
    "address":{
      "street":"706 Northampton Dr",
      "city":"Cary",
      "state":"North Carolina",
      "zip": "27513"
    },
    "website": "http://www.timbakerdev.com",
    "resumedownload":"http://timbakerdev.com",
    "social":[
      {
        "name":"facebook",
        "url":"https://github.com/nordicgiant2/react-nice-resume",
        "className":"fa fa-facebook"
      },
      {
        "name":"twitter",
        "url":"http://twitter.com",
        "className":"fa fa-twitter"
      },
      {
        "name":"linkedin",
        "url":"https://www.linkedin.com/in/tim-baker-8420009a/",
        "className":"fa fa-linkedin"
      },
      {
        "name":"instagram",
        "url":"http://instagram.com/tbaker_x",
        "className":"fa fa-instagram"
      },
      {
        "name":"github",
        "url":"https://github.com/joychen5069",
        "className":"fa fa-github"
      }
    ]
  },
  "resume":{
    "skillmessage":"Here you can create a short write-up of your skills to show off to employers",
    "education":[
      {
        "school":"University of North Carolina-Chapel Hill",
        "degree":"Certificate in ",
        "graduated":"August 2020",
        "description":"Describe your experience at school, what you learned, what useful skills you have acquired etc."
      },
      {
        "school":"University of North Carolina-Chapel Hill",
        "degree":"BA in Peace, War, and Defense",
        "graduated":"May 2017",
        "description":"Describe your experience at school, what you learned, what useful skills you have acquired etc."
      }
    ],
    "work":[
      {
        "company":"Awesome Design Studio",
        "title":"Senior UX God ",
        "years":"March 2010 - Present",
        "description":"Describe work, special projects, notable achievements, what technologies you have been working with, and anything else that would be useful for an employer to know."
      },
      {
        "company":"Super Cool Studio",
        "title":"Junior bug fixer",
        "years":"March 2007 - February 2010",
        "description":"Describe work, special projects, notable achievements, what technologies you have been working with, and anything else that would be useful for an employer to know."
      }
    ],
    "skills":[
      {
        "name":"JavaScript",
        "level":"80%"
      },
     {
        "name":"ReactJs",
        "level":"50%"
      },
      {
        "name":"CSS",
        "level":"90%"
      },
      {
        "name":"HTML",
        "level":"90%"
      },
      {
        "name":"NodeJS",
        "level":"50%"
      }
    ]
  },
  "portfolio":{
    "projects": [
      {
        "title":"Book Club Tracker",
        "category":"Keep track of what your club is reading",
        "image":"bookClubDemo.gif",
        "url":"https://book-club-application.herokuapp.com/"
      },
      {
        "title":"Date Night",
        "category":"Decide what you and your date are eating tonight",
        "image":"datenightdemo.gif",
        "url":"https://joychen5069.github.io/Date-Night/"
      },
      {
        "title":"Burger Eater",
        "category":"A project that allows you to eat burgers",
        "image":"burgerDemo.gif",
        "url":"https://eat-the-burger-by-joy-chen.herokuapp.com/"
      },
      {
        "title":"Password Generator",
        "category":"Create a random password for your security",
        "image":"passwordGenerator.jpg",
        "url":"https://joychen5069.github.io/RandomPasswordGenerator/"
      },
      {
        "title":"Weather Application",
        "category":"Check the weather of any city you want",
        "image":"Weather-Api.png",
        "url":"https://joychen5069.github.io/WeatherForcast/"
      }
    ]
  }
}
